mixupy/__init__.py
mixupy/mixup.py
mixupy-0.1.2.dist-info/LICENSE
mixupy-0.1.2.dist-info/WHEEL
mixupy-0.1.2.dist-info/METADATA
mixupy-0.1.2.dist-info/RECORD
