Metadata-Version: 2.1
Name: mixupy
Version: 0.1.2
Summary: Data augmentation with the mixup method
Home-page: https://github.com/makeyourownmaker/mixupy
Author: makeyourownmaker
Author-email: makeyourownmaker@gmx.com
Requires-Python: >=3.7
Classifier: License :: OSI Approved :: GNU General Public License v3 or later (GPLv3+)
Classifier: Programming Language :: Python :: 3
